[
    {
        "key": "group_69dfb395e488c",
        "title": "Movie fields",
        "fields": [
            {
                "key": "field_69dfb396040b1",
                "label": "Release date",
                "name": "release_date",
                "aria-label": "",
                "type": "date_picker",
                "instructions": "",
                "required": 0,
                "conditional_logic": 0,
                "wrapper": {
                    "width": "",
                    "class": "",
                    "id": ""
                },
                "display_format": "d\/m\/Y",
                "return_format": "d\/m\/Y",
                "first_day": 1,
                "default_to_current_date": 1,
                "allow_in_bindings": 0
            },
            {
                "key": "field_69dfb403040b3",
                "label": "Year of release",
                "name": "year_of_release",
                "aria-label": "",
                "type": "number",
                "instructions": "",
                "required": 0,
                "conditional_logic": 0,
                "wrapper": {
                    "width": "",
                    "class": "",
                    "id": ""
                },
                "default_value": "",
                "min": "",
                "max": "",
                "allow_in_bindings": 0,
                "placeholder": "",
                "step": "",
                "prepend": "",
                "append": ""
            },
            {
                "key": "field_69dfb3d0040b2",
                "label": "Rating",
                "name": "rating",
                "aria-label": "",
                "type": "number",
                "instructions": "",
                "required": 0,
                "conditional_logic": 0,
                "wrapper": {
                    "width": "",
                    "class": "",
                    "id": ""
                },
                "default_value": "",
                "min": "",
                "max": "",
                "allow_in_bindings": 0,
                "placeholder": "",
                "step": "",
                "prepend": "",
                "append": ""
            }
        ],
        "location": [
            [
                {
                    "param": "post_type",
                    "operator": "==",
                    "value": "movie"
                }
            ]
        ],
        "menu_order": 0,
        "position": "normal",
        "style": "default",
        "label_placement": "top",
        "instruction_placement": "label",
        "hide_on_screen": "",
        "active": true,
        "description": "",
        "show_in_rest": 0,
        "display_title": "",
        "allow_ai_access": false,
        "ai_description": ""
    }
]
